tonto2/#tonto2_main.py#
tonto2/__init__.py
tonto2/tonto2_conv_adr.py
tonto2/tonto2_conv_cal.py
tonto2/tonto2_main.py
tonto2/tonto2_main.py~
tonto2/externals/__init__.py
tonto2/externals/barcodes2.py
tonto2/externals/q0.py
tonto2/externals/tonto2_code_tables.py
tonto2/externals/tonto2_conv_common.py
tonto2/externals/tonto2_parse_international_addresses.py
tonto2-2.1.36.data/data/Tonto2/tonto.code_tables.ini
tonto2-2.1.36.dist-info/entry_points.txt
tonto2-2.1.36.dist-info/licenses/LICENSE
tonto2-2.1.36.dist-info/WHEEL
tonto2-2.1.36.dist-info/METADATA
tonto2-2.1.36.dist-info/RECORD
