Metadata-Version: 2.4
Name: tonto2
Version: 2.1.36
Summary: Tonto2 is a personal address-list, calendar, notepad, and so much more.
Keywords: Addresses,Appointments,Bibliographies,Bibliography,Bookmarks,Calendars,Card files,Contacts,Favorites,Lists,Notes,Note taking,Offline,PIM,PKMS,Passwords,People,Personal Information Manager,Personal Information Management,Personal Knowledge Manager,Personal Knowledge Management,Phone Numbers,Privacy,Productivity,Rolodex,Standalone,Telephone Numbers
Author-email: Chuck Rhode <CRhode@LacusVeris.com>
Requires-Python: >=3.9
Classifier: License :: OSI Approved :: GNU General Public License v3 or later (GPLv3+)
Classifier: Development Status :: 3 - Alpha
Classifier: Environment :: X11 Applications :: Qt
Classifier: Intended Audience :: End Users/Desktop
Classifier: Natural Language :: English
Classifier: Operating System :: Microsoft :: Windows
Classifier: Operating System :: Unix
Classifier: Programming Language :: Python :: 3
Classifier: Topic :: Utilities
License-File: LICENSE
Requires-Dist: PyQt5
Requires-Dist: dateparser
Requires-Dist: vobject
Project-URL: Home, https://LacusVeris.com/Tonto2/Docs/en
